pycox/__init__.py
pycox/utils.py
pycox/datasets/__init__.py
pycox/datasets/_dataset_loader.py
pycox/datasets/from_deepsurv.py
pycox/datasets/from_kkbox.py
pycox/datasets/from_rdatasets.py
pycox/datasets/from_simulations.py
pycox/evaluation/__init__.py
pycox/evaluation/admin.py
pycox/evaluation/concordance.py
pycox/evaluation/eval_surv.py
pycox/evaluation/ipcw.py
pycox/evaluation/metrics.py
pycox/models/__init__.py
pycox/models/base.py
pycox/models/bce_surv.py
pycox/models/cox.py
pycox/models/cox_cc.py
pycox/models/cox_time.py
pycox/models/data.py
pycox/models/deephit.py
pycox/models/interpolation.py
pycox/models/logistic_hazard.py
pycox/models/loss.py
pycox/models/mtlr.py
pycox/models/pc_hazard.py
pycox/models/pmf.py
pycox/models/utils.py
pycox/preprocessing/__init__.py
pycox/preprocessing/discretization.py
pycox/preprocessing/feature_transforms.py
pycox/preprocessing/label_transforms.py
pycox/simulations/__init__.py
pycox/simulations/base.py
pycox/simulations/discrete_logit_hazard.py
pycox/simulations/relative_risk.py
pycox-0.3.0.dist-info/LICENSE
pycox-0.3.0.dist-info/METADATA
pycox-0.3.0.dist-info/WHEEL
pycox-0.3.0.dist-info/top_level.txt
pycox-0.3.0.dist-info/RECORD
